MANIFEST.in
README.md
README.rst
setup.cfg
setup.py
bme280_exporter/__about__.py
bme280_exporter/__init__.py
bme280_exporter/__main__.py
bme280_exporter/exporter.py
bme280_exporter.egg-info/PKG-INFO
bme280_exporter.egg-info/SOURCES.txt
bme280_exporter.egg-info/dependency_links.txt
bme280_exporter.egg-info/entry_points.txt
bme280_exporter.egg-info/requires.txt
bme280_exporter.egg-info/top_level.txt