Metadata-Version: 1.1
Name: bme280-exporter
Version: 0.1.0
Summary: Prometheus exporter for the Bosh BME280 sensor
Home-page: https://github.com/ashtreefarms/bme280_exporter
Author: Jake Krog
Author-email: jake.krog@gmail.com
License: MIT
Keywords: raspberry pi,rpi,prometheus,BME280,i2c,temperature,humidity,pressure
Platform: UNKNOWN
Classifier: Development Status :: 4 - Beta
Classifier: Environment :: Console
Classifier: Intended Audience :: Education
Classifier: Intended Audience :: Developers
Classifier: License :: OSI Approved :: MIT License
Classifier: Programming Language :: Python :: 3
Classifier: Topic :: System :: Monitoring
